.gitignore
.gitlab-ci.yml
CHANGELOG.md
LICENSE
README.md
setup.py
example/input/observations.csv
example/input/observations.yaml
example/input/recommendations.csv
example/input/recommendations.yaml
example/output/donut.png
example/output/grid.png
example/output/recommendations.png
rpg/__init__.py
rpg/__main__.py
rpg/data/grid-bg.png
rpg/data/recommendations-bg.png
rpg_0bs1d1an.egg-info/PKG-INFO
rpg_0bs1d1an.egg-info/SOURCES.txt
rpg_0bs1d1an.egg-info/dependency_links.txt
rpg_0bs1d1an.egg-info/entry_points.txt
rpg_0bs1d1an.egg-info/requires.txt
rpg_0bs1d1an.egg-info/top_level.txt