Metadata-Version: 2.1
Name: rpg-0bs1d1an
Version: 0.0.10
Summary: Risk plot generator
Home-page: https://gitlab.com/0bs1d1an/rpg
Author: Guido Kroon (@0bs1d1an)
Author-email: gkroon@maelstrom.ninja
License: UNKNOWN
Project-URL: Bug Reports, https://gitlab.com/0bs1d1an/rpg/issues
Project-URL: Source, https://gitlab.com/0bs1d1an/rpg/
Platform: UNKNOWN
Classifier: Development Status :: 3 - Alpha
Classifier: Intended Audience :: Information Technology
Classifier: Intended Audience :: System Administrators
Classifier: Topic :: Security
Classifier: License :: OSI Approved :: GNU General Public License v3 (GPLv3)
Classifier: Operating System :: OS Independent
Classifier: Programming Language :: Python :: 3
Classifier: Programming Language :: Python :: 3.6
Classifier: Programming Language :: Python :: 3.7
Requires-Python: >=3.6
